{
  "project_info": {
    "project_number": "354377351589",
    "project_id": "wheeldecideapp",
    "storage_bucket": "wheeldecideapp.appspot.com"
  },
  "client": [
    {
      "client_info": {
        "mobilesdk_app_id": "1:354377351589:android:c139459523ced9b3bbe84c",
        "android_client_info": {
          "package_name": "com.example.wheel_decide_app"
        }
      },
      "oauth_client": [
        {
          "client_id": "354377351589-je7v1g5v3ga4lrf0e27bf5lfvh0kk3s1.apps.googleusercontent.com",
          "client_type": 3
        }
      ],
      "api_key": [
        {
          "current_key": "AIzaSyB7vkQYlksindTaFxrZ3wsAtAWsfKWRLiI"
        }
      ],
      "services": {
        "appinvite_service": {
          "other_platform_oauth_client": [
            {
              "client_id": "354377351589-je7v1g5v3ga4lrf0e27bf5lfvh0kk3s1.apps.googleusercontent.com",
              "client_type": 3
            }
          ]
        }
      }
    }
  ],
  "configuration_version": "1"
}